genomixhub/__init__.py
genomixhub/genomixhub.py
genomixhub/tests/__init__.py
genomixhub/tests/conftest.py
genomixhub/tests/test_dev_frame.py
genomixhub/tests/test_load_frame.py
genomixhub/tests/test_prod_frame.py
genomixhub_api-1.0.0rc5.dist-info/LICENSE.md
genomixhub_api-1.0.0rc5.dist-info/METADATA
genomixhub_api-1.0.0rc5.dist-info/WHEEL
genomixhub_api-1.0.0rc5.dist-info/entry_points.txt
genomixhub_api-1.0.0rc5.dist-info/RECORD
