Metadata-Version: 2.1
Name: genomixhub-api
Version: 1.0.0rc5
Summary: genomixhub-api integrates genomics information into GenomiXHub reports.
Home-page: https://pypi.org/project/genomixhub-api
License: MIT
Author: GenomiXHub
Author-email: dev@genomixhub.com
Requires-Python: >=3.8,<4.0
Classifier: Development Status :: 1 - Planning
Classifier: License :: OSI Approved :: MIT License
Classifier: Natural Language :: English
Classifier: Operating System :: OS Independent
Classifier: Programming Language :: Python
Classifier: Programming Language :: Python :: 3
Classifier: Programming Language :: Python :: 3.8
Classifier: Programming Language :: Python :: 3.9
Classifier: Programming Language :: Python :: 3.10
Classifier: Programming Language :: Python :: 3.11
Requires-Dist: click
Requires-Dist: minilog
Project-URL: Documentation, https://genomixhub-api.readthedocs.io
Project-URL: Repository, https://github.com/n-kostadinov/genomixhub-api
